opencue_proto/comment_pb2.py
opencue_proto/comment_pb2_grpc.py
opencue_proto/criterion_pb2.py
opencue_proto/criterion_pb2_grpc.py
opencue_proto/cue_pb2.py
opencue_proto/cue_pb2_grpc.py
opencue_proto/department_pb2.py
opencue_proto/department_pb2_grpc.py
opencue_proto/depend_pb2.py
opencue_proto/depend_pb2_grpc.py
opencue_proto/facility_pb2.py
opencue_proto/facility_pb2_grpc.py
opencue_proto/filter_pb2.py
opencue_proto/filter_pb2_grpc.py
opencue_proto/host_pb2.py
opencue_proto/host_pb2_grpc.py
opencue_proto/job_pb2.py
opencue_proto/job_pb2_grpc.py
opencue_proto/limit_pb2.py
opencue_proto/limit_pb2_grpc.py
opencue_proto/renderPartition_pb2.py
opencue_proto/renderPartition_pb2_grpc.py
opencue_proto/report_pb2.py
opencue_proto/report_pb2_grpc.py
opencue_proto/rqd_pb2.py
opencue_proto/rqd_pb2_grpc.py
opencue_proto/service_pb2.py
opencue_proto/service_pb2_grpc.py
opencue_proto/show_pb2.py
opencue_proto/show_pb2_grpc.py
opencue_proto/subscription_pb2.py
opencue_proto/subscription_pb2_grpc.py
opencue_proto/task_pb2.py
opencue_proto/task_pb2_grpc.py
opencue_proto-1.13.8.dist-info/METADATA
opencue_proto-1.13.8.dist-info/WHEEL
opencue_proto-1.13.8.dist-info/RECORD
