Metadata-Version: 2.1
Name: opencue_proto
Version: 1.13.8
Summary: The opencue-proto is a module containing the protobuf modules for communication to and from Cuebot.
Requires-Python: >3.7
Requires-Dist: grpcio-tools>=1.62.0
Requires-Dist: grpcio>=1.62.0
